GoSqlShujukuJiaocheng/README.md
GoSqlShujukuJiaocheng/__init__.py
GoSqlShujukuJiaocheng/__main__.py
GoSqlShujukuJiaocheng/file.epub
GoSqlShujukuJiaocheng/index.html
GoSqlShujukuJiaocheng/css/__init__.py
GoSqlShujukuJiaocheng/css/annotations.css
GoSqlShujukuJiaocheng/css/main.css
GoSqlShujukuJiaocheng/css/normalize.css
GoSqlShujukuJiaocheng/css/popup.css
GoSqlShujukuJiaocheng/font/__init__.py
GoSqlShujukuJiaocheng/font/fontello.eot
GoSqlShujukuJiaocheng/font/fontello.svg
GoSqlShujukuJiaocheng/font/fontello.ttf
GoSqlShujukuJiaocheng/font/fontello.woff
GoSqlShujukuJiaocheng/img/__init__.py
GoSqlShujukuJiaocheng/img/annotator-glyph-sprite.png
GoSqlShujukuJiaocheng/img/annotator-icon-sprite.png
GoSqlShujukuJiaocheng/img/apple-touch-icon.png
GoSqlShujukuJiaocheng/img/cancelfullscreen.png
GoSqlShujukuJiaocheng/img/close.png
GoSqlShujukuJiaocheng/img/fullscreen.png
GoSqlShujukuJiaocheng/img/loader.gif
GoSqlShujukuJiaocheng/img/menu-icon.png
GoSqlShujukuJiaocheng/img/save.png
GoSqlShujukuJiaocheng/img/saved.png
GoSqlShujukuJiaocheng/img/settings-s.png
GoSqlShujukuJiaocheng/img/settings.png
GoSqlShujukuJiaocheng/img/star.png
GoSqlShujukuJiaocheng/js/__init__.py
GoSqlShujukuJiaocheng/js/epub.js
GoSqlShujukuJiaocheng/js/epub.min.js
GoSqlShujukuJiaocheng/js/epub.min.map
GoSqlShujukuJiaocheng/js/hooks.min.js
GoSqlShujukuJiaocheng/js/hooks.min.map
GoSqlShujukuJiaocheng/js/reader.js
GoSqlShujukuJiaocheng/js/reader.js.map
GoSqlShujukuJiaocheng/js/reader.min.js
GoSqlShujukuJiaocheng/js/reader.min.map
GoSqlShujukuJiaocheng/js/hooks/__init__.py
GoSqlShujukuJiaocheng/js/hooks/extensions/__init__.py
GoSqlShujukuJiaocheng/js/hooks/extensions/highlight.js
GoSqlShujukuJiaocheng/js/libs/__init__.py
GoSqlShujukuJiaocheng/js/libs/jquery.min.js
GoSqlShujukuJiaocheng/js/libs/localforage.min.js
GoSqlShujukuJiaocheng/js/libs/screenfull.js
GoSqlShujukuJiaocheng/js/libs/screenfull.min.js
GoSqlShujukuJiaocheng/js/libs/zip.min.js
GoSqlShujukuJiaocheng/js/plugins/__init__.py
go_sql_shujuku_jiaocheng-2024.3.6.0.dist-info/METADATA
go_sql_shujuku_jiaocheng-2024.3.6.0.dist-info/WHEEL
go_sql_shujuku_jiaocheng-2024.3.6.0.dist-info/entry_points.txt
go_sql_shujuku_jiaocheng-2024.3.6.0.dist-info/top_level.txt
go_sql_shujuku_jiaocheng-2024.3.6.0.dist-info/RECORD
